<?xml version="1.0" encoding="UTF-8"?>
<!DOCTYPE hibernate-mapping PUBLIC "-//Hibernate/Hibernate Mapping DTD 3.0//EN" "http://www.hibernate.org/dtd/hibernate-mapping-3.0.dtd">
<!-- Generated 28-10-2015 22:20:53 by Hibernate Tools 4.3.1 -->
<hibernate-mapping>
  <class catalog="BDserviciotecnico" name="modelo.entidades.Equipo" optimistic-lock="version" schema="dbo" table="EQUIPO">
    <id name="imei" type="string">
      <column length="8" name="IMEI"/>
      <generator class="assigned"/>
    </id>
    <property name="marca" type="string">
      <column length="50" name="MARCA"/>
    </property>
    <property name="modelo" type="string">
      <column length="60" name="MODELO"/>
    </property>
    <set fetch="select" inverse="true" lazy="true" name="ordenTrabajos" table="ORDEN_TRABAJO">
      <key>
        <column length="8" name="IMEI" not-null="true"/>
      </key>
      <one-to-many class="modelo.entidades.OrdenTrabajo"/>
    </set>
  </class>
</hibernate-mapping>
